{
  "$schema": "https://schema.tauri.app/config/2",
  "productName": "Orkia Forge Viewer",
  "version": "0.1.0",
  "identifier": "app.orkia.forge.viewer",
  "build": {
    "frontendDist": "dist"
  },
  "app": {
    "withGlobalTauri": true,
    "windows": [],
    "security": {
      "csp": "default-src 'none'; script-src 'self' 'unsafe-inline'; style-src 'self' 'unsafe-inline'; img-src 'self' data:; font-src 'self' data:; connect-src 'none'; frame-src 'none'; base-uri 'none'; form-action 'none'",
      "assetProtocol": {
        "enable": false,
        "scope": {
          "allow": [],
          "deny": []
        }
      }
    }
  },
  "bundle": {
    "active": false,
    "targets": [],
    "icon": []
  }
}
